CHANGES.txt
LICENSE.txt
README.txt
setup.py
version.txt
raisin/__init__.py
raisin.recipe.extract.egg-info/PKG-INFO
raisin.recipe.extract.egg-info/SOURCES.txt
raisin.recipe.extract.egg-info/dependency_links.txt
raisin.recipe.extract.egg-info/entry_points.txt
raisin.recipe.extract.egg-info/namespace_packages.txt
raisin.recipe.extract.egg-info/not-zip-safe
raisin.recipe.extract.egg-info/requires.txt
raisin.recipe.extract.egg-info/top_level.txt
raisin/recipe/__init__.py
raisin/recipe/extract/__init__.py
raisin/recipe/extract/accessions.py
raisin/recipe/extract/annotations.py
raisin/recipe/extract/files.py
raisin/recipe/extract/genomes.py
raisin/recipe/extract/profiles.py
raisin/recipe/extract/replicates.py
raisin/recipe/extract/runs.py
raisin/recipe/extract/utils.py
raisin/recipe/extract/tests/README.txt
raisin/recipe/extract/tests/__init__.py
raisin/recipe/extract/tests/test_recipe.py